plagchecker/__init__.py
plagchecker-1.0.1.dist-info/METADATA
plagchecker-1.0.1.dist-info/WHEEL
plagchecker-1.0.1.dist-info/top_level.txt
plagchecker-1.0.1.dist-info/RECORD
