Metadata-Version: 2.1
Name: plagchecker
Version: 1.0.1
Summary: plagchecker focuses on using wwww.prepostseo.com plagairism checker facility.
Home-page: UNKNOWN
Author: Shrey Patel
Author-email: dailycodingpro@gmail.com
License: MIT
Keywords: plagairism,checker,plagairismchecker,prepostseo,seo
Platform: UNKNOWN
Classifier: License :: OSI Approved :: MIT License
Classifier: Programming Language :: Python :: 2
Classifier: Programming Language :: Python :: 3
Classifier: Programming Language :: Python :: 3.7
Classifier: Programming Language :: Python :: 3.8
